README.rst
setup.py
tornado_hbredis/__init__.py
tornado_hbredis/tornado_hbredis.py
tornado_hbredis.egg-info/PKG-INFO
tornado_hbredis.egg-info/SOURCES.txt
tornado_hbredis.egg-info/dependency_links.txt
tornado_hbredis.egg-info/requires.txt
tornado_hbredis.egg-info/top_level.txt